gvision/__init__.py
gvision/gvision.py
google_vision_wrapper-0.0.2.dist-info/LICENSE.txt
google_vision_wrapper-0.0.2.dist-info/METADATA
google_vision_wrapper-0.0.2.dist-info/WHEEL
google_vision_wrapper-0.0.2.dist-info/top_level.txt
google_vision_wrapper-0.0.2.dist-info/RECORD
