Metadata-Version: 2.1
Name: google-vision-wrapper
Version: 0.0.2
Summary: Tiny Python wrapper for Google Vision API. Query google vision API and obtain information in pandas DataFrame in few lines of code.
Home-page: https://github.com/gcgrossi/google-vision-wrapper
Author: Giulio Cornelio Grossi, Ph.D.
Author-email: giulio.cornelio.grossi@gmail.com
License: MIT
Platform: UNKNOWN
Requires-Dist: google-cloud-vision (>2)
Requires-Dist: opencv-python
Requires-Dist: pandas
Requires-Dist: numpy
